ucsc/__init__.py
ucsc/api.py
ucsc/test.py
ucsc_genomic_data-1.0.0.dist-info/LICENSE
ucsc_genomic_data-1.0.0.dist-info/METADATA
ucsc_genomic_data-1.0.0.dist-info/WHEEL
ucsc_genomic_data-1.0.0.dist-info/top_level.txt
ucsc_genomic_data-1.0.0.dist-info/RECORD
